MANIFEST.in
README.rst
requirements.txt
setup.cfg
setup.py
versioneer.py
avionix_airflow/__init__.py
avionix_airflow/_version.py
avionix_airflow/build_airflow.py
avionix_airflow/conftest.py
avionix_airflow/host_settings.py
avionix_airflow/py.typed
avionix_airflow/teardown_cluster.py
avionix_airflow.egg-info/PKG-INFO
avionix_airflow.egg-info/SOURCES.txt
avionix_airflow.egg-info/dependency_links.txt
avionix_airflow.egg-info/not-zip-safe
avionix_airflow.egg-info/requires.txt
avionix_airflow.egg-info/top_level.txt
avionix_airflow/docker/__init__.py
avionix_airflow/docker/_build_image.py
avionix_airflow/docker/airflow/Dockerfile
avionix_airflow/docker/airflow/config/airflow.cfg
avionix_airflow/docker/airflow/script/entrypoint.sh
avionix_airflow/kubernetes/__init__.py
avionix_airflow/kubernetes/base_ingress_path.py
avionix_airflow/kubernetes/base_service.py
avionix_airflow/kubernetes/namespace_meta.py
avionix_airflow/kubernetes/orchestration.py
avionix_airflow/kubernetes/probes.py
avionix_airflow/kubernetes/services.py
avionix_airflow/kubernetes/utils.py
avionix_airflow/kubernetes/value_handler.py
avionix_airflow/kubernetes/airflow/__init__.py
avionix_airflow/kubernetes/airflow/airflow_containers.py
avionix_airflow/kubernetes/airflow/airflow_options.py
avionix_airflow/kubernetes/airflow/airflow_orchestrator.py
avionix_airflow/kubernetes/airflow/airflow_pods.py
avionix_airflow/kubernetes/airflow/airflow_roles.py
avionix_airflow/kubernetes/airflow/airflow_secrets.py
avionix_airflow/kubernetes/airflow/airflow_service_accounts.py
avionix_airflow/kubernetes/airflow/airflow_storage.py
avionix_airflow/kubernetes/airflow/airflow_worker_pod_template.py
avionix_airflow/kubernetes/airflow/dag_retrieval.py
avionix_airflow/kubernetes/airflow/ingress_controller.py
avionix_airflow/kubernetes/cloud/__init__.py
avionix_airflow/kubernetes/cloud/cloud_options.py
avionix_airflow/kubernetes/cloud/aws/__init__.py
avionix_airflow/kubernetes/cloud/aws/aws_options.py
avionix_airflow/kubernetes/cloud/aws/elastic_search_proxy/__init__.py
avionix_airflow/kubernetes/cloud/aws/elastic_search_proxy/proxy_deployment.py
avionix_airflow/kubernetes/cloud/aws/elastic_search_proxy/proxy_service.py
